[
    {
        "type": "pgd_eps_0.1",
        "train_losses": [
            2.3040291905403136,
            2.3039607849121095
        ],
        "train_accuracies": [
            0.10176,
            0.09826
        ],
        "test_accuracies": [
            0.1
        ],
        "test_precisions": [
            0.01
        ],
        "test_recall": [
            0.1
        ],
        "test_f1_scores": [
            0.01818181818181818
        ]
    },
    {
        "type": "pgd_eps_0.2",
        "train_losses": [
            2.3038751001358033,
            2.3038880157470705
        ],
        "train_accuracies": [
            0.10114,
            0.10082
        ],
        "test_accuracies": [
            0.1
        ],
        "test_precisions": [
            0.01
        ],
        "test_recall": [
            0.1
        ],
        "test_f1_scores": [
            0.01818181818181818
        ]
    },
    {
        "type": "pgd_eps_0.4",
        "train_losses": [
            2.3038890023231504,
            2.3039339308738707
        ],
        "train_accuracies": [
            0.09944,
            0.10022
        ],
        "test_accuracies": [
            0.1
        ],
        "test_precisions": [
            0.01
        ],
        "test_recall": [
            0.1
        ],
        "test_f1_scores": [
            0.01818181818181818
        ]
    }
]